apophenia/__init__.py
apophenia/main.py
apophenia/api/__init__.py
apophenia/api/discuss.py
apophenia/api/extract.py
apophenia/cmds/__init__.py
apophenia/cmds/discuss.py
apophenia/cmds/extract.py
apophenia-0.2.1.dist-info/METADATA
apophenia-0.2.1.dist-info/WHEEL
apophenia-0.2.1.dist-info/entry_points.txt
apophenia-0.2.1.dist-info/licenses/LICENSE
apophenia-0.2.1.dist-info/RECORD
